MavenRumenjiaochengCYuyanBianchengWangFix1/README.md
MavenRumenjiaochengCYuyanBianchengWangFix1/__init__.py
MavenRumenjiaochengCYuyanBianchengWangFix1/__main__.py
MavenRumenjiaochengCYuyanBianchengWangFix1/file.epub
MavenRumenjiaochengCYuyanBianchengWangFix1/index.html
MavenRumenjiaochengCYuyanBianchengWangFix1/css/__init__.py
MavenRumenjiaochengCYuyanBianchengWangFix1/css/annotations.css
MavenRumenjiaochengCYuyanBianchengWangFix1/css/main.css
MavenRumenjiaochengCYuyanBianchengWangFix1/css/normalize.css
MavenRumenjiaochengCYuyanBianchengWangFix1/css/popup.css
MavenRumenjiaochengCYuyanBianchengWangFix1/font/__init__.py
MavenRumenjiaochengCYuyanBianchengWangFix1/font/fontello.eot
MavenRumenjiaochengCYuyanBianchengWangFix1/font/fontello.svg
MavenRumenjiaochengCYuyanBianchengWangFix1/font/fontello.ttf
MavenRumenjiaochengCYuyanBianchengWangFix1/font/fontello.woff
MavenRumenjiaochengCYuyanBianchengWangFix1/img/__init__.py
MavenRumenjiaochengCYuyanBianchengWangFix1/img/annotator-glyph-sprite.png
MavenRumenjiaochengCYuyanBianchengWangFix1/img/annotator-icon-sprite.png
MavenRumenjiaochengCYuyanBianchengWangFix1/img/apple-touch-icon.png
MavenRumenjiaochengCYuyanBianchengWangFix1/img/cancelfullscreen.png
MavenRumenjiaochengCYuyanBianchengWangFix1/img/close.png
MavenRumenjiaochengCYuyanBianchengWangFix1/img/fullscreen.png
MavenRumenjiaochengCYuyanBianchengWangFix1/img/loader.gif
MavenRumenjiaochengCYuyanBianchengWangFix1/img/menu-icon.png
MavenRumenjiaochengCYuyanBianchengWangFix1/img/save.png
MavenRumenjiaochengCYuyanBianchengWangFix1/img/saved.png
MavenRumenjiaochengCYuyanBianchengWangFix1/img/settings-s.png
MavenRumenjiaochengCYuyanBianchengWangFix1/img/settings.png
MavenRumenjiaochengCYuyanBianchengWangFix1/img/star.png
MavenRumenjiaochengCYuyanBianchengWangFix1/js/__init__.py
MavenRumenjiaochengCYuyanBianchengWangFix1/js/epub.js
MavenRumenjiaochengCYuyanBianchengWangFix1/js/epub.min.js
MavenRumenjiaochengCYuyanBianchengWangFix1/js/epub.min.map
maven_rumenjiaocheng_c_yuyan_biancheng_wang_fix1-2025.3.24.1.dist-info/METADATA
maven_rumenjiaocheng_c_yuyan_biancheng_wang_fix1-2025.3.24.1.dist-info/WHEEL
maven_rumenjiaocheng_c_yuyan_biancheng_wang_fix1-2025.3.24.1.dist-info/entry_points.txt
maven_rumenjiaocheng_c_yuyan_biancheng_wang_fix1-2025.3.24.1.dist-info/top_level.txt
maven_rumenjiaocheng_c_yuyan_biancheng_wang_fix1-2025.3.24.1.dist-info/RECORD
